ccsd/__init__.py
ccsd/diffusion.py
ccsd/data/__init__.py
ccsd/data/data_generators.py
ccsd/data/preprocess.py
ccsd/data/preprocess_for_nspdk.py
ccsd/data/utils/__init__.py
ccsd/data/utils/data_frame_parser.py
ccsd/data/utils/numpytupledataset.py
ccsd/data/utils/smile_to_graph.py
ccsd/src/__init__.py
ccsd/src/losses.py
ccsd/src/sampler.py
ccsd/src/sde.py
ccsd/src/solver.py
ccsd/src/trainer.py
ccsd/src/evaluation/__init__.py
ccsd/src/evaluation/eden.py
ccsd/src/evaluation/mmd.py
ccsd/src/evaluation/stats.py
ccsd/src/models/ScoreNetwork_A.py
ccsd/src/models/ScoreNetwork_A_Base_CC.py
ccsd/src/models/ScoreNetwork_A_CC.py
ccsd/src/models/ScoreNetwork_F.py
ccsd/src/models/ScoreNetwork_X.py
ccsd/src/models/__init__.py
ccsd/src/models/attention.py
ccsd/src/models/hodge_attention.py
ccsd/src/models/hodge_layers.py
ccsd/src/models/layers.py
ccsd/src/parsers/__init__.py
ccsd/src/parsers/config.py
ccsd/src/parsers/parser.py
ccsd/src/parsers/parser_generator.py
ccsd/src/parsers/parser_preprocess.py
ccsd/src/utils/__init__.py
ccsd/src/utils/cc_utils.py
ccsd/src/utils/data_loader.py
ccsd/src/utils/data_loader_mol.py
ccsd/src/utils/ema.py
ccsd/src/utils/errors.py
ccsd/src/utils/graph_utils.py
ccsd/src/utils/loader.py
ccsd/src/utils/logger.py
ccsd/src/utils/models_utils.py
ccsd/src/utils/mol_utils.py
ccsd/src/utils/plot.py
ccsd/src/utils/print.py
ccsd/src/utils/time_utils.py
ccsd-0.3.3.dist-info/AUTHORS
ccsd-0.3.3.dist-info/LICENSE
ccsd-0.3.3.dist-info/METADATA
ccsd-0.3.3.dist-info/WHEEL
ccsd-0.3.3.dist-info/top_level.txt
ccsd-0.3.3.dist-info/RECORD
