Metadata-Version: 2.1
Name: ccsd
Version: 0.3.3
Summary: CCSD (Combinatorial Complex Score-based Diffusion) is a sophisticated score-based diffusion model designed to generate Combinatorial Complexes using Stochastic Differential Equations. This cutting-edge approach enables the generation of complex objects with higher-order structures and relations, thereby enhancing our ability to learn underlying distributions and produce more realistic objects.
Home-page: https://ccsd.readthedocs.io/en/latest/
Download-URL: https://pypi.org/project/ccsd/
Author: Adrien Carrel
Author-email: a.carrel@hotmail.fr
Maintainer: Adrien Carrel
Maintainer-email: a.carrel@hotmail.fr
License: MIT
Project-URL: Bug Tracker, https://github.com/AdrienC21/CCSD/issues
Project-URL: Documentation, https://ccsd.readthedocs.io/en/latest/
Project-URL: Source Code, https://github.com/AdrienC21/CCSD
Keywords: ccsd,python,diffusion-models,combinatorial-complex,score-based-generative-models,score-based-generative-modelingtopological-deep-learning,higher-order-models,tdl,molecule,molecule-generation,machine-learning,deep-learning,graph-neural-networks,graph,topology,diffusion,artificial-intelligence,topological-neural-networks,topological-data-analysis
Classifier: Development Status :: 2 - Pre-Alpha
Classifier: Intended Audience :: Developers
Classifier: Intended Audience :: Science/Research
Classifier: Operating System :: Microsoft :: Windows
Classifier: Operating System :: MacOS :: MacOS X
Classifier: Operating System :: Unix
Classifier: License :: OSI Approved :: MIT License
Classifier: Programming Language :: Python :: 3
Classifier: Programming Language :: Python :: 3 :: Only
Classifier: Programming Language :: Python :: 3.7
Classifier: Topic :: Scientific/Engineering
Classifier: Topic :: Scientific/Engineering :: Artificial Intelligence
Classifier: Topic :: Scientific/Engineering :: Mathematics
Classifier: Topic :: Software Development
Classifier: Topic :: Software Development :: Libraries
Classifier: Topic :: Software Development :: Libraries :: Python Modules
Requires-Python: >=3.10
License-File: LICENSE
License-File: AUTHORS
Requires-Dist: dill >=0.3.6
Requires-Dist: easydict >=1.10
Requires-Dist: freezegun >=1.2.2
Requires-Dist: hypernetx >=1.2.5
Requires-Dist: imageio >=2.31.1
Requires-Dist: joblib >=1.3.1
Requires-Dist: kaleido >=0.1.0.post1
Requires-Dist: matplotlib >=3.7.2
Requires-Dist: molsets >=0.3.1
Requires-Dist: networkx >=2.8.8
Requires-Dist: numpy >=1.24.4
Requires-Dist: pandas >=2.0.3
Requires-Dist: plotly >=5.15.0
Requires-Dist: pyemd >=1.0.0
Requires-Dist: pytest >=7.4.0
Requires-Dist: pytz >=2023.3
Requires-Dist: pyyaml >=6.0
Requires-Dist: rdkit >=2023.3.2
Requires-Dist: scikit-learn >=1.3.0
Requires-Dist: scipy >=1.11.1
Requires-Dist: toponetx
Requires-Dist: torch >=2.0.1
Requires-Dist: tqdm >=4.65.0
Requires-Dist: wandb
Requires-Dist: molsets
Requires-Dist: pytest-cov
